generate_heatmap/__init__.py
generate_heatmap/command.py
generate_heatmap/config.py
generate_heatmap/generate.py
generate_heatmap/heatmap.py
generate_heatmap/process.py
generate_heatmap-0.2.1.dist-info/DESCRIPTION.rst
generate_heatmap-0.2.1.dist-info/METADATA
generate_heatmap-0.2.1.dist-info/RECORD
generate_heatmap-0.2.1.dist-info/WHEEL
generate_heatmap-0.2.1.dist-info/entry_points.txt
generate_heatmap-0.2.1.dist-info/metadata.json
generate_heatmap-0.2.1.dist-info/top_level.txt
