Metadata-Version: 2.0
Name: generate-heatmap
Version: 0.2.1
Summary: Generate heatmap from the video for usage analysis.
Home-page: https://github.com/ajayrawat12/generate_heatmap
Author: Ajay Rawat
Author-email: ajayrawat12@outlook.com
License: Apache 2.0
Keywords: Generate Heatmap from video
Platform: UNKNOWN
Classifier: Development Status :: 3 - Alpha
Classifier: Programming Language :: Python :: 3.6
Classifier: Intended Audience :: Developers
Classifier: Topic :: Software Development :: Build Tools
Requires-Dist: asn1crypto (==0.24.0)
Requires-Dist: certifi (==2018.1.18)
Requires-Dist: cffi (==1.11.4)
Requires-Dist: chardet (==3.0.4)
Requires-Dist: cryptography (==2.1.4)
Requires-Dist: cycler (==0.10.0)
Requires-Dist: idna (==2.6)
Requires-Dist: Markdown (==2.6.11)
Requires-Dist: matplotlib (==2.1.2)
Requires-Dist: numpy (==1.14.1)
Requires-Dist: pycosat (==0.6.3)
Requires-Dist: pycparser (==2.18)
Requires-Dist: pyOpenSSL (==17.5.0)
Requires-Dist: pyparsing (==2.2.0)
Requires-Dist: PySocks (==1.6.7)
Requires-Dist: python-dateutil (==2.6.1)
Requires-Dist: pytz (==2018.3)
Requires-Dist: requests (==2.18.4)
Requires-Dist: six (==1.11.0)
Requires-Dist: urllib3 (==1.22)
